psqlmodel/__init__.py
psqlmodel/__main__.py
psqlmodel/cli_config.py
psqlmodel/py.typed
psqlmodel/utils.py
psqlmodel/core/__init__.py
psqlmodel/core/engine.py
psqlmodel/core/session.py
psqlmodel/core/transactions.py
psqlmodel/db/__init__.py
psqlmodel/db/notify.py
psqlmodel/db/replication.py
psqlmodel/db/subscriber.py
psqlmodel/db/trigger_functions.py
psqlmodel/db/trigger_helpers.py
psqlmodel/db/triggers.py
psqlmodel/integrations/__init__.py
psqlmodel/integrations/http.py
psqlmodel/integrations/kafka.py
psqlmodel/integrations/middlewares.py
psqlmodel/integrations/redis.py
psqlmodel/migrations/__init__.py
psqlmodel/migrations/config.py
psqlmodel/migrations/ddl_generator.py
psqlmodel/migrations/diff.py
psqlmodel/migrations/differ.py
psqlmodel/migrations/exceptions.py
psqlmodel/migrations/hasher.py
psqlmodel/migrations/manager.py
psqlmodel/migrations/migration.py
psqlmodel/migrations/model_generator.py
psqlmodel/migrations/state.py
psqlmodel/migrations/status.py
psqlmodel/orm/__init__.py
psqlmodel/orm/column.py
psqlmodel/orm/model.py
psqlmodel/orm/model.pyi
psqlmodel/orm/relationships.py
psqlmodel/orm/table.py
psqlmodel/orm/types.py
psqlmodel/query/__init__.py
psqlmodel/query/builder.py
psqlmodel/query/crud.py
psqlmodel/query/insert_select_proxy.py
psqlmodel/query/layout.py
psqlmodel/scripts/.gitlab-ci.yml
psqlmodel/scripts/pre-commit
psqlmodel-0.9.29.dist-info/METADATA
psqlmodel-0.9.29.dist-info/WHEEL
psqlmodel-0.9.29.dist-info/entry_points.txt
psqlmodel-0.9.29.dist-info/licenses/LICENSE
psqlmodel-0.9.29.dist-info/RECORD
