Metadata-Version: 2.4
Name: psqlmodel
Version: 0.9.29
Summary: A modern, lightweight async PostgreSQL ORM with QueryBuilder, migrations, and trigger support
Project-URL: Homepage, https://github.com/roilanlg05/psqlmodel
Project-URL: Documentation, https://github.com/roilanlg05/psqlmodel#readme
Project-URL: Repository, https://github.com/roilanlg05/psqlmodel.git
Project-URL: Issues, https://github.com/roilanlg05/psqlmodel/issues
Project-URL: Changelog, https://github.com/roilanlg05/psqlmodel/releases
Author-email: Hashdown <user@example.com>
License-Expression: MIT
License-File: LICENSE
Keywords: async,asyncpg,database,migrations,orm,postgresql,psycopg,query-builder,triggers
Classifier: Development Status :: 4 - Beta
Classifier: Framework :: AsyncIO
Classifier: Intended Audience :: Developers
Classifier: License :: OSI Approved :: MIT License
Classifier: Operating System :: OS Independent
Classifier: Programming Language :: Python :: 3
Classifier: Programming Language :: Python :: 3.9
Classifier: Programming Language :: Python :: 3.10
Classifier: Programming Language :: Python :: 3.11
Classifier: Programming Language :: Python :: 3.12
Classifier: Programming Language :: Python :: 3.13
Classifier: Programming Language :: Python :: 3.14
Classifier: Topic :: Database
Classifier: Topic :: Database :: Front-Ends
Classifier: Topic :: Software Development :: Libraries :: Python Modules
Classifier: Typing :: Typed
Requires-Python: >=3.9
Requires-Dist: psycopg[binary]>=3.1.0
Requires-Dist: python-dotenv>=1.0.0
Provides-Extra: all
Requires-Dist: asyncpg>=0.28.0; extra == 'all'
Requires-Dist: black>=23.0.0; extra == 'all'
Requires-Dist: mypy>=1.0.0; extra == 'all'
Requires-Dist: orjson>=3.9.0; extra == 'all'
Requires-Dist: pytest-asyncio>=0.21.0; extra == 'all'
Requires-Dist: pytest>=7.0.0; extra == 'all'
Requires-Dist: ruff>=0.1.0; extra == 'all'
Provides-Extra: async
Requires-Dist: asyncpg>=0.28.0; extra == 'async'
Provides-Extra: dev
Requires-Dist: black>=23.0.0; extra == 'dev'
Requires-Dist: mypy>=1.0.0; extra == 'dev'
Requires-Dist: pytest-asyncio>=0.21.0; extra == 'dev'
Requires-Dist: pytest>=7.0.0; extra == 'dev'
Requires-Dist: ruff>=0.1.0; extra == 'dev'
Provides-Extra: fast
Requires-Dist: orjson>=3.9.0; extra == 'fast'
